Metadata-Version: 2.4
Name: mseep-mcp-reddit
Version: 0.1.4
Summary: A Reddit client using PRAW
Author-email: mseep <support@skydeck.ai>
Requires-Python: >=3.13
License-File: LICENSE
Requires-Dist: aiohttp>=3.11.18
Requires-Dist: fastmcp>=2.2.0
Requires-Dist: mcp[cli]>=1.6.0
Requires-Dist: praw>=7.7.1
Requires-Dist: python-dotenv>=1.0.0
Requires-Dist: rich>=13.7.0
Dynamic: license-file
